pyservo42c/__init__.py
pyservo42c/demo.py
pyservo42c/servo42c.py
pyservo42c/servo42cTCPUartBridge.py
pyservo42c/servo42cUart.py
pyservo42c-0.2.1.dist-info/licenses/LICENSE.md
pyservo42c-0.2.1.dist-info/METADATA
pyservo42c-0.2.1.dist-info/WHEEL
pyservo42c-0.2.1.dist-info/top_level.txt
pyservo42c-0.2.1.dist-info/RECORD
