Metadata-Version: 2.4
Name: pyservo42c
Version: 0.2.1
Summary: A Python library for interfacing with the MKS Servo42C closed-loop stepper.
Author-email: Travis Howse <tjhowse@gmail.com>
License-Expression: GPL-3.0-or-later
Project-URL: homepage, https://github.com/tjhowse/pyservo42c
Project-URL: repository, https://github.com/tjhowse/pyservo42c
Keywords: servo,stepper,motor,closed-loop,MKS
Requires-Python: >=3.7
License-File: LICENSE.md
Provides-Extra: dev
Requires-Dist: pytest; extra == "dev"
Requires-Dist: build; extra == "dev"
Requires-Dist: black; extra == "dev"
Requires-Dist: twine; extra == "dev"
Provides-Extra: serial
Requires-Dist: pyserial; extra == "serial"
Dynamic: license-file
